{
    "id": "4F5807D1",
    "title": {
        "full": "PDC World Champ Darts",
        "reduced": "PDC World Champ Darts"
    },
    "genre": [
        "Sports & Recreation"
    ],
    "developer": "Mere Mortals",
    "publisher": "O Games",
    "release_date": "2008-01-01",
    "user_rating": null,
    "description": {
        "full": "Go head-to-head with the greatest PDC Champions in the year’s most fierce console Championship: PDC World Championship Darts - Pure excitement, Pure pressure, Pure Darts",
        "short": "Go head-to-head with the greatest PDC Champions in the year’s most fierce console Championship: PDC World Championship Darts - Pure excitement, Pure pressure, Pure Darts"
    },
    "media": [
        {
            "media_id": "3F83E7F8",
            "title": "PDC World Championship Darts",
            "edition": "Original",
            "region": "Europe"
        }
    ],
    "artwork": {
        "background": "http://download.xbox.com/content/images/66acd000-77fe-1000-9115-d8024f5807d1/1033/background.jpg",
        "banner": "http://download.xbox.com/content/images/66acd000-77fe-1000-9115-d8024f5807d1/1033/banner.png",
        "boxart": "http://download.xbox.com/content/images/66acd000-77fe-1000-9115-d8024f5807d1/1033/boxartlg.jpg",
        "icon": "http://download.xbox.com/content/images/66acd000-77fe-1000-9115-d8024f5807d1/1033/tile.png",
        "gallery": []
    },
    "products": {
        "parent": [],
        "related": []
    }
}