{
    "id": "585501E4",
    "title": {
        "full": "Terwilliger",
        "reduced": "Terwilliger"
    },
    "genre": [
        "Family"
    ],
    "developer": "domric",
    "publisher": "domric",
    "release_date": null,
    "user_rating": "3.25",
    "description": {
        "full": "This game was classified by the community with the following category scores - Violence=0/3, Sex=0/3, Mature Content=0/3. Terwilliger is the neighborhood mouse catcher. He catches mice and shows the neighbors his good deeds. Some people in the neighborhood appreciate his efforts... but some do not! How many mice can you help Terwilliger catch?",
        "short": "Terwilliger is the neighborhood mouse catcher. He catches mice and shows the neighbors his good deeds. Some people in the neighborhood appreciate his efforts... but some do not! How many mice can you help Terwilliger catch?"
    },
    "media": [],
    "artwork": {
        "background": null,
        "banner": "http://avatar.xboxlive.com/global/t.585501e4/marketplace/0/1",
        "boxart": "http://download.xbox.com:80/content/xna/assets/585501E4_World/xboxboxart.jpg",
        "icon": "http://avatar.xboxlive.com/global/t.585501e4/icon/0/8000",
        "gallery": [
            "http://download.xbox.com:80/content/xna/assets/585501E4_World/screen1.jpg"
        ]
    },
    "products": {
        "parent": [],
        "related": []
    }
}