{
    "id": "5841088F",
    "title": {
        "full": "Discs Of Tron",
        "reduced": "Discs Of Tron"
    },
    "genre": [
        "Classics"
    ],
    "developer": "Digital Eclipse",
    "publisher": "Disney Interactive Studios",
    "release_date": "2010-01-05",
    "user_rating": "3.50",
    "description": {
        "full": "Single Player, Xbox LIVE Multiplayer 1-2, Local Multiplayer 1-2, HD (High Definition). The arcade classic is back!  Play Discs Of Tron and battle Sark for video-warrior supremacy.  Twelve levels of disc-hurling action await! There are no refunds for this item. For more information, see www.xbox.com/Live/accounts.",
        "short": "Take on the role of the mighty video warrior Tron as you face off against the insidious Sark in the game arena. Dodge and deflect Sark’s attacks as you attempt to derezz him with a well aimed disc. Unlock the full version to gain access to the full game, multiplayer modes, and the ability to compare scores on the leaderboards!"
    },
    "media": [],
    "artwork": {
        "background": "http://download.xbox.com/content/images/66acd000-77fe-1000-9115-d8025841088f/1033/background.jpg",
        "banner": "http://download.xbox.com/content/images/66acd000-77fe-1000-9115-d8025841088f/1033/banner.png",
        "boxart": "http://download.xbox.com/content/images/66acd000-77fe-1000-9115-d8025841088f/1033/boxartlg.jpg",
        "icon": "http://download.xbox.com/content/images/66acd000-77fe-1000-9115-d8025841088f/1033/tile.png",
        "gallery": [
            "http://download.xbox.com/content/images/66acd000-77fe-1000-9115-d8025841088f/1033/screenlg1.jpg",
            "http://download.xbox.com/content/images/66acd000-77fe-1000-9115-d8025841088f/1033/screenlg2.jpg",
            "http://download.xbox.com/content/images/66acd000-77fe-1000-9115-d8025841088f/1033/screenlg3.jpg",
            "http://download.xbox.com/content/images/66acd000-77fe-1000-9115-d8025841088f/1033/screenlg4.jpg",
            "http://download.xbox.com/content/images/66acd000-77fe-1000-9115-d8025841088f/1033/screenlg5.jpg"
        ]
    },
    "products": {
        "parent": [],
        "related": []
    }
}