{
    "id": "585509EC",
    "title": {
        "full": "Star Defender",
        "reduced": "Star Defender"
    },
    "genre": [
        "Action & Adventure"
    ],
    "developer": "Andrew French",
    "publisher": "Andrew French",
    "release_date": null,
    "user_rating": "3.50",
    "description": {
        "full": "This game was classified by the community with the following category scores - Violence=0/3, Sex=0/3, Mature Content=0/3. Fly through space to defend the stars as you create black holes and edit the very fabrics of time.",
        "short": "Fly through space to defend the stars as you create black holes and edit the very fabrics of time."
    },
    "media": [],
    "artwork": {
        "background": null,
        "banner": "http://avatar.xboxlive.com/global/t.584e07d2/marketplace/0/585509ec00000001",
        "boxart": "http://download.xbox.com:80/content/xna/assets/585509EC_World/xboxboxart.jpg",
        "icon": "http://avatar.xboxlive.com/global/t.585509ec/icon/0/8000",
        "gallery": [
            "http://download.xbox.com:80/content/xna/assets/585509EC_World/screen1.jpg",
            "http://download.xbox.com:80/content/xna/assets/585509EC_World/screen2.jpg",
            "http://download.xbox.com:80/content/xna/assets/585509EC_World/screen3.jpg"
        ]
    },
    "products": {
        "parent": [],
        "related": []
    }
}