{
    "id": "41560888",
    "title": {
        "full": "Tony Hawk SHRED",
        "reduced": "TONY HAWK SHRED"
    },
    "genre": [
        "Sports & Recreation"
    ],
    "developer": "Robomodo",
    "publisher": "Activision",
    "release_date": "2010-10-26",
    "user_rating": "0.00",
    "description": {
        "full": "GET ON BOARD AND GO BIG! Experience some of the biggest air and tricks seen in an action sports video game. Tony Hawk®: SHRED's motion sensing skateboard/snowboard allows players to control the action with their feet to perform amazing tricks in the game. Using the board as a skateboard, clear huge gaps, hit massive drops, and ride out roller coaster grinds. Using the board as a snowboard, speed down mountain peaks filled with breathtaking big airs, crazy spins and incredible flips. The game's intuitive controls and multiple difficulty levels make it easy to pick up and play. It’s time to SHRED.",
        "short": "GET ON BOARD AND GO BIG! Experience some of the biggest air and tricks seen in an action sports video game. Tony Hawk®: SHRED's motion sensing skateboard/snowboard allows players to control the action with their feet to perform amazing tricks in the game. Using the board as a skateboard, clear huge gaps, hit massive drops, and ride out roller coaster grinds. Using the board as a snowboard, speed down mountain peaks filled with breathtaking big airs, crazy spins and incredible flips. The game's …"
    },
    "media": [
        {
            "media_id": "4E241263",
            "title": "Tony Hawk: Shred",
            "edition": "Original",
            "region": "USA"
        }
    ],
    "artwork": {
        "background": "http://download.xbox.com/content/images/66acd000-77fe-1000-9115-d80241560888/1033/background.jpg",
        "banner": "http://download.xbox.com/content/images/66acd000-77fe-1000-9115-d80241560888/1033/banner.png",
        "boxart": "http://download.xbox.com/content/images/66acd000-77fe-1000-9115-d80241560888/1033/boxartlg.jpg",
        "icon": "http://download.xbox.com/content/images/66acd000-77fe-1000-9115-d80241560888/1033/tile.png",
        "gallery": []
    },
    "products": {
        "parent": [],
        "related": []
    }
}