{
    "id": "58550893",
    "title": {
        "full": "Techno Kitten Adventure",
        "reduced": "Techno Kitten Adventure"
    },
    "genre": [
        "Music"
    ],
    "developer": "21 Street Games LLC",
    "publisher": "21 Street Games LLC",
    "release_date": null,
    "user_rating": "4.25",
    "description": {
        "full": "This game was classified by the community with the following category scores - Violence=0/3, Sex=0/3, Mature Content=0/3. Navigate a kitten by jetpack, fueled by hopes and dreams, through a fantastical world of techno music. *New Graphics *New Levels *New Kittehs *New Music = U Can Has: 1. DREAM Featuring Frisco – Sea of Love (Hixxy Remix) 2. CLOUD Featuring Re-Con – Like A Rainbow 3. LAVA Featuring Styles & Breeze – You’re Shining 4. MEAT Featuring  F.R.E.A.K. - Hungry For Your Love + 13 NEW Kittehs!",
        "short": "Navigate a kitten by jetpack, fueled by hopes and dreams, through a fantastical world of techno music. *New Graphics *New Levels *New Kittehs *New Music = U Can Has: 1. DREAM Featuring Frisco – Sea of Love (Hixxy Remix) 2. CLOUD Featuring Re-Con – Like A Rainbow 3. LAVA Featuring Styles & Breeze – You’re Shining 4. MEAT Featuring  F.R.E.A.K. - Hungry For Your Love + 13 NEW Kittehs!"
    },
    "media": [],
    "artwork": {
        "background": null,
        "banner": "http://avatar.xboxlive.com/global/t.584e07d2/marketplace/0/5855089300000001",
        "boxart": "http://download.xbox.com:80/content/xna/assets/58550893_World/xboxboxart.jpg",
        "icon": "http://avatar.xboxlive.com/global/t.58550893/icon/0/8000",
        "gallery": [
            "http://download.xbox.com:80/content/xna/assets/58550893_World/screen2.jpg",
            "http://download.xbox.com:80/content/xna/assets/58550893_World/screen3.jpg",
            "http://download.xbox.com:80/content/xna/assets/58550893_World/screen4.jpg",
            "http://download.xbox.com:80/content/xna/assets/58550893_World/screen1.jpg"
        ]
    },
    "products": {
        "parent": [],
        "related": []
    }
}