{
    "id": "5855098C",
    "title": {
        "full": "SteamSunk",
        "reduced": "SteamSunk"
    },
    "genre": [
        "Action & Adventure"
    ],
    "developer": "Snape",
    "publisher": "Snape",
    "release_date": null,
    "user_rating": "3.25",
    "description": {
        "full": "This game was classified by the community with the following category scores - Violence=1/3, Sex=0/3, Mature Content=0/3. SteamSunk is a 3D top-down shooter with arena based game-play. The game is set in a sea environment, with the player controlling a ship and the enemies represented by various flying machines which try to sink you. With random power-ups and levels, super-weapons, bosses and much more your SteamSunk experience is different each time.",
        "short": "SteamSunk is a 3D top-down shooter with arena based game-play. The game is set in a sea environment, with the player controlling a ship and the enemies represented by various flying machines which try to sink you. With random power-ups and levels, super-weapons, bosses and much more your SteamSunk experience is different each time."
    },
    "media": [],
    "artwork": {
        "background": null,
        "banner": "http://avatar.xboxlive.com/global/t.584e07d2/marketplace/0/5855098c00000001",
        "boxart": "http://download.xbox.com:80/content/xna/assets/5855098C_World/xboxboxart.jpg",
        "icon": "http://avatar.xboxlive.com/global/t.5855098c/icon/0/8000",
        "gallery": [
            "http://download.xbox.com:80/content/xna/assets/5855098C_World/screen3.jpg",
            "http://download.xbox.com:80/content/xna/assets/5855098C_World/screen4.jpg",
            "http://download.xbox.com:80/content/xna/assets/5855098C_World/screen1.jpg",
            "http://download.xbox.com:80/content/xna/assets/5855098C_World/screen2.jpg"
        ]
    },
    "products": {
        "parent": [],
        "related": []
    }
}