{
    "id": "584107ED",
    "title": {
        "full": "Geometry Wars Retro Evolved",
        "reduced": "Geometry Wars Evolved"
    },
    "genre": [
        "Action & Adventure"
    ],
    "developer": "Bizarre Creations Ltd",
    "publisher": "Microsoft Studios",
    "release_date": "2010-01-05",
    "user_rating": "4.25",
    "description": {
        "full": "Single Player, HD (High Definition) Geometry Wars became an instant classic when it first appeared in the Project Gotham Racing® 2. This exclusive Xbox Live Arcade sequel gives you both the original Retro version and a new Evolved mode, which combines modern graphics with old-school fun. There are no refunds for this item. For more information, see www.xbox.com/live/accounts.",
        "short": "Super charged retro shooting meets next gen graphics. Power up your weapons, build up your multipliers and rack up the points to prove you’ve got the skills to be the best."
    },
    "media": [],
    "artwork": {
        "background": "http://download.xbox.com/content/images/66acd000-77fe-1000-9115-d802584107ed/1033/background.jpg",
        "banner": "http://download.xbox.com/content/images/66acd000-77fe-1000-9115-d802584107ed/1033/banner.png",
        "boxart": "http://download.xbox.com/content/images/66acd000-77fe-1000-9115-d802584107ed/1033/boxartlg.jpg",
        "icon": "http://download.xbox.com/content/images/66acd000-77fe-1000-9115-d802584107ed/1033/tile.png",
        "gallery": [
            "http://download.xbox.com/content/images/66acd000-77fe-1000-9115-d802584107ed/1033/screenlg1.jpg",
            "http://download.xbox.com/content/images/66acd000-77fe-1000-9115-d802584107ed/1033/screenlg2.jpg",
            "http://download.xbox.com/content/images/66acd000-77fe-1000-9115-d802584107ed/1033/screenlg3.jpg",
            "http://download.xbox.com/content/images/66acd000-77fe-1000-9115-d802584107ed/1033/screenlg4.jpg",
            "http://download.xbox.com/content/images/66acd000-77fe-1000-9115-d802584107ed/1033/screenlg5.jpg"
        ]
    },
    "products": {
        "parent": [],
        "related": []
    }
}