{
    "id": "57528821",
    "title": {
        "full": "Gotham City Impostors Beta",
        "reduced": "Gotham City Impostors Beta"
    },
    "genre": [
        "Shooter"
    ],
    "developer": "Monolith Productions",
    "publisher": "WB Games, Inc.",
    "release_date": "2011-12-13",
    "user_rating": null,
    "description": {
        "full": "Download and play the Gotham City Impostors beta now!  A 6 vs. 6 first person shooter, Gotham City Impostors is a multiplayer game unlike any other, giving players the opportunity to rebel against conformity as they customize their own characters. Posing as amateur vigilantes or villains, gamers create their own Bats and The Jokerz characters using unprecedented customization options including insane costumes, homebrewed gadgets and a wide range of traditional and imagined weapons.",
        "short": "Download and play the Gotham City Impostors beta now! "
    },
    "media": [],
    "artwork": {
        "background": "http://download.xbox.com/content/images/66acd000-77fe-1000-9115-d80257528821/1033/background.jpg",
        "banner": "http://download.xbox.com/content/images/66acd000-77fe-1000-9115-d80257528821/1033/banner.png",
        "boxart": "http://download.xbox.com/content/images/66acd000-77fe-1000-9115-d80257528821/1033/boxartlg.jpg",
        "icon": "http://download.xbox.com/content/images/66acd000-77fe-1000-9115-d80257528821/1033/tile.png",
        "gallery": []
    },
    "products": {
        "parent": [
            {
                "id": "57520820",
                "title": "Gotham City Impostors Beta"
            }
        ],
        "related": []
    }
}