{
    "id": "4D5389C2",
    "title": {
        "full": "Fable III Demo",
        "reduced": "Fable III Demo"
    },
    "genre": [
        "Action & Adventure",
        "Strategy & Simulation"
    ],
    "developer": "Lionhead Studios",
    "publisher": "Microsoft Game Studios",
    "release_date": "2011-05-17",
    "user_rating": "3.75",
    "description": {
        "full": "Fable III is the next blockbuster installment in the highly praised Fable franchise. Lead a revolution to take control of Albion, fight alongside your people, and experience love and loss while preparing to defend the kingdom against a looming threat. Your choices as ruler will lead to consequences felt across the entire land. ",
        "short": "Fable III is the next blockbuster installment in the highly praised Fable franchise. Lead a revolution to take control of Albion, fight alongside your people, and experience love and loss while preparing to defend the kingdom against a looming threat. Your choices as ruler will lead to consequences felt across the entire land. "
    },
    "media": [],
    "artwork": {
        "background": "http://download.xbox.com/content/images/66acd000-77fe-1000-9115-d8024d5389c2/1033/background.jpg",
        "banner": "http://download.xbox.com/content/images/66acd000-77fe-1000-9115-d8024d5389c2/1033/banner.png",
        "boxart": "http://download.xbox.com/content/images/66acd000-77fe-1000-9115-d8024d5389c2/1033/boxartlg.jpg",
        "icon": "http://download.xbox.com/content/images/66acd000-77fe-1000-9115-d8024d5389c2/1033/tile.png",
        "gallery": []
    },
    "products": {
        "parent": [
            {
                "id": "4D5308D6",
                "title": "Fable III"
            }
        ],
        "related": []
    }
}